src/verilog/fifo_sync/fifo_sync.v
`timescale 1ns/1ps

module fifo_sync 
    #(
        parameter DATA_WIDTH = 32,
        parameter ADDR_BITS = 4
    )
    (
        (* direct_reset = "true" *) input wire resetn_i,
        (* direct_enable = "true" *) input wire clk_i,
        input wire [DATA_WIDTH-1:0] data_in,
        output wire [DATA_WIDTH-1:0] data_out,
        input wire w_en,
        input wire r_en,
        output wire fifo_empty,
        output wire fifo_full
    );

    localparam N_REGS = 2**ADDR_BITS;

    reg w_en_r, r_en_r;
    reg [ADDR_BITS-1:0] w_ptr_r;
    reg [ADDR_BITS-1:0] r_ptr_r;
    reg [DATA_WIDTH-1:0] fifo_mem_reg [N_REGS-1:0];

    wire w_ptr_overflow = (r_ptr_r > w_ptr_r) ? 1'b1 : 1'b0;

    assign fifo_empty = (w_ptr_r == r_ptr_r);
    assign fifo_full = ((w_ptr_r == (N_REGS - 1)) && (!r_ptr_r));
    
    assign data_out = (r_en_r) ? fifo_mem_reg[r_ptr_r] : {{DATA_WIDTH}{1'b0}};

    always @(posedge clk_i)
    begin
        if (! resetn_i) 
        begin
            w_en_r <= 0;
            r_en_r <= 0;
        end
        else
        begin
            w_en_r <= w_en;
            r_en_r <= r_en;
        end
    end

    integer i;
    always @(posedge clk_i)
    begin
        if (! resetn_i) begin
            for (i = 0; i < N_REGS; i = i + 1)
                fifo_mem_reg[i] <= 0;

            w_ptr_r <= 0;
        end
        else
        begin
            if (w_en_r && !fifo_full) begin
                w_ptr_r <= w_ptr_r + 1;

                fifo_mem_reg[w_ptr_r] <= data_in;
            end
        end
    end

    always @(posedge clk_i)
    begin
        if (! resetn_i)
            r_ptr_r <= 0;
        else
        begin
            if (r_en_r == 1'b1)
            begin
                if (w_ptr_overflow)
                    r_ptr_r <= r_ptr_r + 1;
                else begin
                    if ((r_ptr_r + 1) > (w_ptr_r))
                        r_ptr_r <= w_ptr_r;
                    else
                        r_ptr_r <= r_ptr_r + 1;
                end
            end
        end
    end

endmodule

src/verilog/fifo_sync_tb/fifo_sync_tb.v
`timescale 1ns/1ps

module fifo_sync_tb();

    reg reset_r, clk_r, w_en_r, r_en_r;
    wire fifo_full_w, fifo_empty_w;

    reg [DATA_WIDTH-1:0] data_in_r;
    wire [DATA_WIDTH-1:0] data_out_w;

    localparam DATA_WIDTH = 8;
    localparam ADDR_BITS = 4;
    localparam N_REGS = 2**ADDR_BITS;

    localparam  RW_ALWAYS = 0,
                W_ALWAYS_R_DELAYED = 1,
                W_NONE_R_ALWAYS = 2,
                WR_NOT_ALIGNED = 3;

    integer test_type = W_ALWAYS_R_DELAYED;

    real r_delay = 2;
    real w_delay = 6;

    fifo_sync #(
        .DATA_WIDTH(DATA_WIDTH),
        .ADDR_BITS(ADDR_BITS)
    ) fifo_sync_inst (
        .resetn_i(reset_r),
        .clk_i(clk_r),
        .data_in(data_in_r),
        .data_out(data_out_w),
        .w_en(w_en_r),
        .r_en(r_en_r),
        .fifo_empty(fifo_empty_w),
        .fifo_full(fifo_full_w)
    );

    integer i, fp;
    initial
    begin
        fp = $fopen("fifo_sync_tb.csv", "w");
        $dumpfile("fifo_sync_tb.vcd");
        $dumpvars(0, fifo_sync_tb);
        for (i = 0; i < N_REGS; i = i + 1)
            $dumpvars(0, fifo_sync_inst.fifo_mem_reg[i]);

        #0 reset_r <= 0; clk_r <= 0; w_en_r <= 0; r_en_r <= 0; data_in_r <= 0;
        #5 reset_r <= 1;

        if (test_type == RW_ALWAYS) begin
            $display("RW_ALWAYS");
            #1 w_en_r <= 1; #r_delay r_en_r <= 1;
            #100 ;
        end
        else if (test_type == W_ALWAYS_R_DELAYED) begin
            $display("W_ALWAYS_R_DELAYED");
            #1 w_en_r <= 1; #r_delay r_en_r <= 1;
            #100 ;
        end
        else if (test_type == W_NONE_R_ALWAYS) begin
            $display("W_NONE_R_ALWAYS");
            #1 r_en_r <= 1;
            #100 ;
        end
        else if (test_type == WR_NOT_ALIGNED) begin
            $display("WR_NOT_ALIGNED");
            #1 w_en_r <= 1; #r_delay r_en_r <= 1; 
            #w_delay w_en_r <= ~w_en_r; #r_delay r_en_r <= ~r_en_r; r_delay = $urandom%16; w_delay = $urandom%16;
            #w_delay w_en_r <= ~w_en_r; #r_delay r_en_r <= ~r_en_r; r_delay = $urandom%16; w_delay = $urandom%16;
            #w_delay w_en_r <= ~w_en_r; #r_delay r_en_r <= ~r_en_r; r_delay = $urandom%16; w_delay = $urandom%16;
            #100 ;
        end

        #1 w_en_r <= 0; r_en_r <= 0;
        #1 $finish; $fclose(fp); 

    end

    always 
    begin
        #0.5 clk_r <= ~clk_r;
    end

    always @(posedge clk_r)
    begin
        data_in_r <= $urandom%255;
        $display("fifo_sync_inst.w_en_r = %1b, fifo_sync_inst.w_ptr_r = %02d, data_in_r = %02d, fifo_sync_inst.r_en_r = %1b, fifo_sync_inst.r_ptr_r,= %02d, data_out_w = %02d", fifo_sync_inst.w_en_r, fifo_sync_inst.w_ptr_r, data_in_r, fifo_sync_inst.r_en_r, fifo_sync_inst.r_ptr_r, data_out_w);        
        $fwrite(fp, "%1b,%02d,%02d,%1b,%02d,%02d\n", fifo_sync_inst.w_en_r, fifo_sync_inst.w_ptr_r, data_in_r, fifo_sync_inst.r_en_r, fifo_sync_inst.r_ptr_r, data_out_w);        
    end

endmodule

iverilog/fifo_sync_tb.vcd
$date
	Thu Sep 15 11:37:25 2022
$end
$version
	Icarus Verilog
$end
$timescale
	1ps
$end
$scope module fifo_sync_tb $end
$var wire 1 ! fifo_full_w $end
$var wire 1 " fifo_empty_w $end
$var wire 8 # data_out_w [7:0] $end
$var reg 1 $ clk_r $end
$var reg 8 % data_in_r [7:0] $end
$var reg 1 & r_en_r $end
$var reg 1 ' reset_r $end
$var reg 1 ( w_en_r $end
$var integer 32 ) fp [31:0] $end
$var integer 32 * i [31:0] $end
$var real 1 + r_delay $end
$var integer 32 , test_type [31:0] $end
$var real 1 - w_delay $end
$scope module fifo_sync_inst $end
$var wire 1 $ clk_i $end
$var wire 8 . data_in [7:0] $end
$var wire 1 ! fifo_full $end
$var wire 1 & r_en $end
$var wire 1 ' resetn_i $end
$var wire 1 ( w_en $end
$var wire 1 / w_ptr_overflow $end
$var wire 1 " fifo_empty $end
$var wire 8 0 data_out [7:0] $end
$var reg 1 1 r_en_r $end
$var reg 4 2 r_ptr_r [3:0] $end
$var reg 1 3 w_en_r $end
$var reg 4 4 w_ptr_r [3:0] $end
$var integer 32 5 i [31:0] $end
$upscope $end
$upscope $end
$scope module fifo_sync_tb $end
$scope module fifo_sync_inst $end
$var reg 8 6 \fifo_mem_reg[0] [7:0] $end
$upscope $end
$upscope $end
$scope module fifo_sync_tb $end
$scope module fifo_sync_inst $end
$var reg 8 7 \fifo_mem_reg[1] [7:0] $end
$upscope $end
$upscope $end
$scope module fifo_sync_tb $end
$scope module fifo_sync_inst $end
$var reg 8 8 \fifo_mem_reg[2] [7:0] $end
$upscope $end
$upscope $end
$scope module fifo_sync_tb $end
$scope module fifo_sync_inst $end
$var reg 8 9 \fifo_mem_reg[3] [7:0] $end
$upscope $end
$upscope $end
$scope module fifo_sync_tb $end
$scope module fifo_sync_inst $end
$var reg 8 : \fifo_mem_reg[4] [7:0] $end
$upscope $end
$upscope $end
$scope module fifo_sync_tb $end
$scope module fifo_sync_inst $end
$var reg 8 ; \fifo_mem_reg[5] [7:0] $end
$upscope $end
$upscope $end
$scope module fifo_sync_tb $end
$scope module fifo_sync_inst $end
$var reg 8 < \fifo_mem_reg[6] [7:0] $end
$upscope $end
$upscope $end
$scope module fifo_sync_tb $end
$scope module fifo_sync_inst $end
$var reg 8 = \fifo_mem_reg[7] [7:0] $end
$upscope $end
$upscope $end
$scope module fifo_sync_tb $end
$scope module fifo_sync_inst $end
$var reg 8 > \fifo_mem_reg[8] [7:0] $end
$upscope $end
$upscope $end
$scope module fifo_sync_tb $end
$scope module fifo_sync_inst $end
$var reg 8 ? \fifo_mem_reg[9] [7:0] $end
$upscope $end
$upscope $end
$scope module fifo_sync_tb $end
$scope module fifo_sync_inst $end
$var reg 8 @ \fifo_mem_reg[10] [7:0] $end
$upscope $end
$upscope $end
$scope module fifo_sync_tb $end
$scope module fifo_sync_inst $end
$var reg 8 A \fifo_mem_reg[11] [7:0] $end
$upscope $end
$upscope $end
$scope module fifo_sync_tb $end
$scope module fifo_sync_inst $end
$var reg 8 B \fifo_mem_reg[12] [7:0] $end
$upscope $end
$upscope $end
$scope module fifo_sync_tb $end
$scope module fifo_sync_inst $end
$var reg 8 C \fifo_mem_reg[13] [7:0] $end
$upscope $end
$upscope $end
$scope module fifo_sync_tb $end
$scope module fifo_sync_inst $end
$var reg 8 D \fifo_mem_reg[14] [7:0] $end
$upscope $end
$upscope $end
$scope module fifo_sync_tb $end
$scope module fifo_sync_inst $end
$var reg 8 E \fifo_mem_reg[15] [7:0] $end
$upscope $end
$upscope $end
$enddefinitions $end
#0
$dumpvars
bx E
bx D
bx C
bx B
bx A
bx @
bx ?
bx >
bx =
bx <
bx ;
bx :
bx 9
bx 8
bx 7
bx 6
bx 5
bx 4
x3
bx 2
x1
bx 0
x/
b0 .
r6 -
b1 ,
r2 +
b10000 *
b10000000000000000000000000000011 )
0(
0'
0&
b0 %
0$
bx #
x"
x!
$end
#500
0/
b0 #
b0 0
0!
01
03
1"
b0 4
b0 E
b0 D
b0 C
b0 B
b0 A
b0 @
b0 ?
b0 >
b0 =
b0 <
b0 ;
b0 :
b0 9
b0 8
b0 7
b0 6
b0 2
b1 %
b1 .
b10000 5
1$
#1000
0$
#1500
b10101001 %
b10101001 .
b0 E
b0 D
b0 C
b0 B
b0 A
b0 @
b0 ?
b0 >
b0 =
b0 <
b0 ;
b0 :
b0 9
b0 8
b0 7
b0 6
b10000 5
1$
#2000
0$
#2500
b0 E
b0 D
b0 C
b0 B
b0 A
b0 @
b0 ?
b0 >
b0 =
b0 <
b0 ;
b0 :
b0 9
b0 8
b0 7
b0 6
b1101000 %
b1101000 .
b10000 5
1$
#3000
0$
#3500
b11011011 %
b11011011 .
b0 E
b0 D
b0 C
b0 B
b0 A
b0 @
b0 ?
b0 >
b0 =
b0 <
b0 ;
b0 :
b0 9
b0 8
b0 7
b0 6
b10000 5
1$
#4000
0$
#4500
b0 E
b0 D
b0 C
b0 B
b0 A
b0 @
b0 ?
b0 >
b0 =
b0 <
b0 ;
b0 :
b0 9
b0 8
b0 7
b0 6
b11001000 %
b11001000 .
b10000 5
1$
#5000
0$
1'
#5500
b11001101 %
b11001101 .
1$
#6000
0$
1(
#6500
13
b11011110 %
b11011110 .
1$
#7000
0$
#7500
b10100100 %
b10100100 .
b11011110 6
0"
b1 4
1$
#8000
0$
1&
#8500
b11011110 #
b11011110 0
11
b10100100 7
b10 4
b1011001 %
b1011001 .
1$
#9000
0$
#9500
b10100100 #
b10100100 0
b111001 %
b111001 .
b1 2
b1011001 8
b11 4
1$
#10000
0$
#10500
b1011001 #
b1011001 0
b111001 9
b100 4
b10 2
b1000111 %
b1000111 .
1$
#11000
0$
#11500
b111001 #
b111001 0
b110111 %
b110111 .
b11 2
b1000111 :
b101 4
1$
#12000
0$
#12500
b1000111 #
b1000111 0
b110111 ;
b110 4
b100 2
b10001 %
b10001 .
1$
#13000
0$
#13500
b110111 #
b110111 0
b1111000 %
b1111000 .
b101 2
b10001 <
b111 4
1$
#14000
0$
#14500
b10001 #
b10001 0
b1111000 =
b1000 4
b110 2
b11011110 %
b11011110 .
1$
#15000
0$
#15500
b1111000 #
b1111000 0
b10000101 %
b10000101 .
b111 2
b11011110 >
b1001 4
1$
#16000
0$
#16500
b11011110 #
b11011110 0
b10000101 ?
b1010 4
b1000 2
b10100100 %
b10100100 .
1$
#17000
0$
#17500
b10000101 #
b10000101 0
b11100101 %
b11100101 .
b1001 2
b10100100 @
b1011 4
1$
#18000
0$
#18500
b10100100 #
b10100100 0
b11100101 A
b1100 4
b1010 2
b10000000 %
b10000000 .
1$
#19000
0$
#19500
b11100101 #
b11100101 0
b11110111 %
b11110111 .
b1011 2
b10000000 B
b1101 4
1$
#20000
0$
#20500
b10000000 #
b10000000 0
b11110111 C
b1110 4
b1100 2
b100100 %
b100100 .
1$
#21000
0$
#21500
b11110111 #
b11110111 0
b100000 %
b100000 .
b1101 2
b100100 D
b1111 4
1$
#22000
0$
#22500
1/
b100100 #
b100100 0
b100000 E
b0 4
b1110 2
b10000110 %
b10000110 .
1$
#23000
0$
#23500
b100000 #
b100000 0
b1000011 %
b1000011 .
b1111 2
b10000110 6
b1 4
1$
#24000
0$
#24500
0/
b10000110 #
b10000110 0
b1000011 7
b10 4
b0 2
b11010111 %
b11010111 .
1$
#25000
0$
#25500
b1000011 #
b1000011 0
b1000001 %
b1000001 .
b1 2
b11010111 8
b11 4
1$
#26000
0$
#26500
b11010111 #
b11010111 0
b1000001 9
b100 4
b10 2
b10101100 %
b10101100 .
1$
#27000
0$
#27500
b1000001 #
b1000001 0
b11010010 %
b11010010 .
b11 2
b10101100 :
b101 4
1$
#28000
0$
#28500
b10101100 #
b10101100 0
b11010010 ;
b110 4
b100 2
b1000111 %
b1000111 .
1$
#29000
0$
#29500
b11010010 #
b11010010 0
b1100101 %
b1100101 .
b101 2
b1000111 <
b111 4
1$
#30000
0$
#30500
b1000111 #
b1000111 0
b1100101 =
b1000 4
b110 2
b11100110 %
b11100110 .
1$
#31000
0$
#31500
b1100101 #
b1100101 0
b10001010 %
b10001010 .
b111 2
b11100110 >
b1001 4
1$
#32000
0$
#32500
b11100110 #
b11100110 0
b10001010 ?
b1010 4
b1000 2
b11110 %
b11110 .
1$
#33000
0$
#33500
b10001010 #
b10001010 0
b110110 %
b110110 .
b1001 2
b11110 @
b1011 4
1$
#34000
0$
#34500
b11110 #
b11110 0
b110110 A
b1100 4
b1010 2
b111110 %
b111110 .
1$
#35000
0$
#35500
b110110 #
b110110 0
b10000101 %
b10000101 .
b1011 2
b111110 B
b1101 4
1$
#36000
0$
#36500
b111110 #
b111110 0
b10000101 C
b1110 4
b1100 2
b1000000 %
b1000000 .
1$
#37000
0$
#37500
b10000101 #
b10000101 0
b1011000 %
b1011000 .
b1101 2
b1000000 D
b1111 4
1$
#38000
0$
#38500
1/
b1000000 #
b1000000 0
b1011000 E
b0 4
b1110 2
b1000 %
b1000 .
1$
#39000
0$
#39500
b1011000 #
b1011000 0
b11111010 %
b11111010 .
b1111 2
b1000 6
b1 4
1$
#40000
0$
#40500
0/
b1000 #
b1000 0
b11111010 7
b10 4
b0 2
b10011110 %
b10011110 .
1$
#41000
0$
#41500
b11111010 #
b11111010 0
b10001 %
b10001 .
b1 2
b10011110 8
b11 4
1$
#42000
0$
#42500
b10011110 #
b10011110 0
b10001 9
b100 4
b10 2
b1100100 %
b1100100 .
1$
#43000
0$
#43500
b10001 #
b10001 0
b10011010 %
b10011010 .
b11 2
b1100100 :
b101 4
1$
#44000
0$
#44500
b1100100 #
b1100100 0
b10011010 ;
b110 4
b100 2
b10010101 %
b10010101 .
1$
#45000
0$
#45500
b10011010 #
b10011010 0
b1101111 %
b1101111 .
b101 2
b10010101 <
b111 4
1$
#46000
0$
#46500
b10010101 #
b10010101 0
b1101111 =
b1000 4
b110 2
b10000010 %
b10000010 .
1$
#47000
0$
#47500
b1101111 #
b1101111 0
b11111101 %
b11111101 .
b111 2
b10000010 >
b1001 4
1$
#48000
0$
#48500
b10000010 #
b10000010 0
b11111101 ?
b1010 4
b1000 2
b10101101 %
b10101101 .
1$
#49000
0$
#49500
b11111101 #
b11111101 0
b11010111 %
b11010111 .
b1001 2
b10101101 @
b1011 4
1$
#50000
0$
#50500
b10101101 #
b10101101 0
b11010111 A
b1100 4
b1010 2
b10011 %
b10011 .
1$
#51000
0$
#51500
b11010111 #
b11010111 0
b11011111 %
b11011111 .
b1011 2
b10011 B
b1101 4
1$
#52000
0$
#52500
b10011 #
b10011 0
b11011111 C
b1110 4
b1100 2
b1011010 %
b1011010 .
1$
#53000
0$
#53500
b11011111 #
b11011111 0
b11000100 %
b11000100 .
b1101 2
b1011010 D
b1111 4
1$
#54000
0$
#54500
1/
b1011010 #
b1011010 0
b11000100 E
b0 4
b1110 2
b1001001 %
b1001001 .
1$
#55000
0$
#55500
b11000100 #
b11000100 0
b1101010 %
b1101010 .
b1111 2
b1001001 6
b1 4
1$
#56000
0$
#56500
0/
b1001001 #
b1001001 0
b1101010 7
b10 4
b0 2
b10110100 %
b10110100 .
1$
#57000
0$
#57500
b1101010 #
b1101010 0
b11111001 %
b11111001 .
b1 2
b10110100 8
b11 4
1$
#58000
0$
#58500
b10110100 #
b10110100 0
b11111001 9
b100 4
b10 2
b11101111 %
b11101111 .
1$
#59000
0$
#59500
b11111001 #
b11111001 0
b10101110 %
b10101110 .
b11 2
b11101111 :
b101 4
1$
#60000
0$
#60500
b11101111 #
b11101111 0
b10101110 ;
b110 4
b100 2
b10010010 %
b10010010 .
1$
#61000
0$
#61500
b10101110 #
b10101110 0
b10101100 %
b10101100 .
b101 2
b10010010 <
b111 4
1$
#62000
0$
#62500
b10010010 #
b10010010 0
b10101100 =
b1000 4
b110 2
b10000010 %
b10000010 .
1$
#63000
0$
#63500
b10101100 #
b10101100 0
b0 %
b0 .
b111 2
b10000010 >
b1001 4
1$
#64000
0$
#64500
b10000010 #
b10000010 0
b0 ?
b1010 4
b1000 2
b1111100 %
b1111100 .
1$
#65000
0$
#65500
b0 #
b0 0
b111111 %
b111111 .
b1001 2
b1111100 @
b1011 4
1$
#66000
0$
#66500
b1111100 #
b1111100 0
b111111 A
b1100 4
b1010 2
b10000101 %
b10000101 .
1$
#67000
0$
#67500
b111111 #
b111111 0
b10001 %
b10001 .
b1011 2
b10000101 B
b1101 4
1$
#68000
0$
#68500
b10000101 #
b10000101 0
b10001 C
b1110 4
b1100 2
b10011 %
b10011 .
1$
#69000
0$
#69500
b10001 #
b10001 0
b10010101 %
b10010101 .
b1101 2
b10011 D
b1111 4
1$
#70000
0$
#70500
1/
b10011 #
b10011 0
b10010101 E
b0 4
b1110 2
b1100000 %
b1100000 .
1$
#71000
0$
#71500
b10010101 #
b10010101 0
b10101110 %
b10101110 .
b1111 2
b1100000 6
b1 4
1$
#72000
0$
#72500
0/
b1100000 #
b1100000 0
b10101110 7
b10 4
b0 2
b111110 %
b111110 .
1$
#73000
0$
#73500
b10101110 #
b10101110 0
b100100 %
b100100 .
b1 2
b111110 8
b11 4
1$
#74000
0$
#74500
b111110 #
b111110 0
b100100 9
b100 4
b10 2
b1100110 %
b1100110 .
1$
#75000
0$
#75500
b100100 #
b100100 0
b10110010 %
b10110010 .
b11 2
b1100110 :
b101 4
1$
#76000
0$
#76500
b1100110 #
b1100110 0
b10110010 ;
b110 4
b100 2
b1101 %
b1101 .
1$
#77000
0$
#77500
b10110010 #
b10110010 0
b1000001 %
b1000001 .
b101 2
b1101 <
b111 4
1$
#78000
0$
#78500
b1101 #
b1101 0
b1000001 =
b1000 4
b110 2
b1010 %
b1010 .
1$
#79000
0$
#79500
b1000001 #
b1000001 0
b10011100 %
b10011100 .
b111 2
b1010 >
b1001 4
1$
#80000
0$
#80500
b1010 #
b1010 0
b10011100 ?
b1010 4
b1000 2
b10101 %
b10101 .
1$
#81000
0$
#81500
b10011100 #
b10011100 0
b1100100 %
b1100100 .
b1001 2
b10101 @
b1011 4
1$
#82000
0$
#82500
b10101 #
b10101 0
b1100100 A
b1100 4
b1010 2
b1001110 %
b1001110 .
1$
#83000
0$
#83500
b1100100 #
b1100100 0
b10011010 %
b10011010 .
b1011 2
b1001110 B
b1101 4
1$
#84000
0$
#84500
b1001110 #
b1001110 0
b10011010 C
b1110 4
b1100 2
b11 %
b11 .
1$
#85000
0$
#85500
b10011010 #
b10011010 0
b111110 %
b111110 .
b1101 2
b11 D
b1111 4
1$
#86000
0$
#86500
1/
b11 #
b11 0
b111110 E
b0 4
b1110 2
b10110010 %
b10110010 .
1$
#87000
0$
#87500
b111110 #
b111110 0
b101111 %
b101111 .
b1111 2
b10110010 6
b1 4
1$
#88000
0$
#88500
0/
b10110010 #
b10110010 0
b101111 7
b10 4
b0 2
b11111 %
b11111 .
1$
#89000
0$
#89500
b101111 #
b101111 0
b11110010 %
b11110010 .
b1 2
b11111 8
b11 4
1$
#90000
0$
#90500
b11111 #
b11111 0
b11110010 9
b100 4
b10 2
b10001111 %
b10001111 .
1$
#91000
0$
#91500
b11110010 #
b11110010 0
b10111100 %
b10111100 .
b11 2
b10001111 :
b101 4
1$
#92000
0$
#92500
b10001111 #
b10001111 0
b10111100 ;
b110 4
b100 2
b10000011 %
b10000011 .
1$
#93000
0$
#93500
b10111100 #
b10111100 0
b11000010 %
b11000010 .
b101 2
b10000011 <
b111 4
1$
#94000
0$
#94500
b10000011 #
b10000011 0
b11000010 =
b1000 4
b110 2
b10001011 %
b10001011 .
1$
#95000
0$
#95500
b11000010 #
b11000010 0
b10010111 %
b10010111 .
b111 2
b10001011 >
b1001 4
1$
#96000
0$
#96500
b10001011 #
b10001011 0
b10010111 ?
b1010 4
b1000 2
b10001 %
b10001 .
1$
#97000
0$
#97500
b10010111 #
b10010111 0
b100000 %
b100000 .
b1001 2
b10001 @
b1011 4
1$
#98000
0$
#98500
b10001 #
b10001 0
b100000 A
b1100 4
b1010 2
b1010001 %
b1010001 .
1$
#99000
0$
#99500
b100000 #
b100000 0
b1011 2
b1010001 B
b1101 4
1$
#100000
0$
#100500
b1010001 #
b1010001 0
b1010001 C
b1110 4
b1100 2
b111101 %
b111101 .
1$
#101000
0$
#101500
b11000100 %
b11000100 .
b1101 2
b111101 D
b1111 4
1$
#102000
0$
#102500
1/
b111101 #
b111101 0
b11000100 E
b0 4
b1110 2
b0 %
b0 .
1$
#103000
0$
#103500
b11000100 #
b11000100 0
b1111011 %
b1111011 .
b1111 2
b0 6
b1 4
1$
#104000
0$
#104500
0/
b0 #
b0 0
b1111011 7
b10 4
b0 2
b1111101 %
b1111101 .
1$
#105000
0$
#105500
b1111011 #
b1111011 0
b1000001 %
b1000001 .
b1 2
b1111101 8
b11 4
1$
#106000
0$
#106500
b1111101 #
b1111101 0
b1000001 9
b100 4
b10 2
b11111011 %
b11111011 .
1$
#107000
0$
#107500
b1000001 #
b1000001 0
b1101 %
b1101 .
b11 2
b11111011 :
b101 4
1$
#108000
0$
#108500
b11111011 #
b11111011 0
b1101 ;
b110 4
b100 2
b11000111 %
b11000111 .
1$
#109000
0$
0&
0(
#109500
b0 #
b0 0
b1110011 %
b1110011 .
b101 2
b11000111 <
b111 4
01
03
1$
