src/verilog/fifo_sync/fifo_sync.v
`timescale 1ns/1ps

module fifo_sync 
    #(
        parameter DATA_WIDTH = 32,
        parameter ADDR_BITS = 4
    )
    (
        (* direct_reset = "true" *) input wire resetn_i,
        (* direct_enable = "true" *) input wire clk_i,
        input wire [DATA_WIDTH-1:0] data_in,
        output wire [DATA_WIDTH-1:0] data_out,
        input wire w_en,
        input wire r_en,
        output wire fifo_empty,
        output wire fifo_full
    );

    localparam N_REGS = 2**ADDR_BITS;

    reg w_en_r, r_en_r;
    reg [ADDR_BITS-1:0] w_ptr_r;
    reg [ADDR_BITS-1:0] r_ptr_r;
    reg [DATA_WIDTH-1:0] fifo_mem_reg [N_REGS-1:0];

    wire w_ptr_overflow = (r_ptr_r > w_ptr_r) ? 1'b1 : 1'b0;

    assign fifo_empty = (w_ptr_r == r_ptr_r);
    assign fifo_full = ((w_ptr_r == (N_REGS - 1)) && (!r_ptr_r));
    
    assign data_out = (r_en_r) ? fifo_mem_reg[r_ptr_r] : {{DATA_WIDTH}{1'b0}};

    always @(posedge clk_i)
    begin
        if (! resetn_i) 
        begin
            w_en_r <= 0;
            r_en_r <= 0;
        end
        else
        begin
            w_en_r <= w_en;
            r_en_r <= r_en;
        end
    end

    integer i;
    always @(posedge clk_i)
    begin
        if (! resetn_i) begin
            for (i = 0; i < N_REGS; i = i + 1)
                fifo_mem_reg[i] <= 0;

            w_ptr_r <= 0;
        end
        else
        begin
            if (w_en_r && !fifo_full) begin
                w_ptr_r <= w_ptr_r + 1;

                fifo_mem_reg[w_ptr_r] <= data_in;
            end
        end
    end

    always @(posedge clk_i)
    begin
        if (! resetn_i)
            r_ptr_r <= 0;
        else
        begin
            if (r_en_r == 1'b1)
            begin
                if (w_ptr_overflow)
                    r_ptr_r <= r_ptr_r + 1;
                else begin
                    if ((r_ptr_r + 1) > (w_ptr_r))
                        r_ptr_r <= w_ptr_r;
                    else
                        r_ptr_r <= r_ptr_r + 1;
                end
            end
        end
    end

endmodule

src/verilog/fifo_sync_tb/fifo_sync_tb.v
`timescale 1ns/1ps

module fifo_sync_tb();

    reg reset_r, clk_r, w_en_r, r_en_r;
    wire fifo_full_w, fifo_empty_w;

    reg [DATA_WIDTH-1:0] data_in_r;
    wire [DATA_WIDTH-1:0] data_out_w;

    localparam DATA_WIDTH = 8;
    localparam ADDR_BITS = 4;
    localparam N_REGS = 2**ADDR_BITS;

    localparam  RW_ALWAYS = 0,
                W_ALWAYS_R_DELAYED = 1,
                W_NONE_R_ALWAYS = 2,
                WR_NOT_ALIGNED = 3;

    integer test_type = W_ALWAYS_R_DELAYED;

    real r_delay = 2;
    real w_delay = 6;

    fifo_sync #(
        .DATA_WIDTH(DATA_WIDTH),
        .ADDR_BITS(ADDR_BITS)
    ) fifo_sync_inst (
        .resetn_i(reset_r),
        .clk_i(clk_r),
        .data_in(data_in_r),
        .data_out(data_out_w),
        .w_en(w_en_r),
        .r_en(r_en_r),
        .fifo_empty(fifo_empty_w),
        .fifo_full(fifo_full_w)
    );

    integer i, fp;
    initial
    begin
        fp = $fopen("fifo_sync_tb.csv", "w");
        $dumpfile("fifo_sync_tb.vcd");
        $dumpvars(0, fifo_sync_tb);
        for (i = 0; i < N_REGS; i = i + 1)
            $dumpvars(0, fifo_sync_inst.fifo_mem_reg[i]);

        #0 reset_r <= 0; clk_r <= 0; w_en_r <= 0; r_en_r <= 0; data_in_r <= 0;
        #5 reset_r <= 1;

        if (test_type == RW_ALWAYS) begin
            $display("RW_ALWAYS");
            #1 w_en_r <= 1; #r_delay r_en_r <= 1;
            #100 ;
        end
        else if (test_type == W_ALWAYS_R_DELAYED) begin
            $display("W_ALWAYS_R_DELAYED");
            #1 w_en_r <= 1; #r_delay r_en_r <= 1;
            #100 ;
        end
        else if (test_type == W_NONE_R_ALWAYS) begin
            $display("W_NONE_R_ALWAYS");
            #1 r_en_r <= 1;
            #100 ;
        end
        else if (test_type == WR_NOT_ALIGNED) begin
            $display("WR_NOT_ALIGNED");
            #1 w_en_r <= 1; #r_delay r_en_r <= 1; 
            #w_delay w_en_r <= ~w_en_r; #r_delay r_en_r <= ~r_en_r; r_delay = $urandom%16; w_delay = $urandom%16;
            #w_delay w_en_r <= ~w_en_r; #r_delay r_en_r <= ~r_en_r; r_delay = $urandom%16; w_delay = $urandom%16;
            #w_delay w_en_r <= ~w_en_r; #r_delay r_en_r <= ~r_en_r; r_delay = $urandom%16; w_delay = $urandom%16;
            #100 ;
        end

        #1 w_en_r <= 0; r_en_r <= 0;
        #1 $finish; $fclose(fp); 

    end

    always 
    begin
        #0.5 clk_r <= ~clk_r;
    end

    always @(posedge clk_r)
    begin
        data_in_r <= $urandom%255;
        $display("fifo_sync_inst.w_en_r = %1b, fifo_sync_inst.w_ptr_r = %02d, data_in_r = %02d, fifo_sync_inst.r_en_r = %1b, fifo_sync_inst.r_ptr_r,= %02d, data_out_w = %02d", fifo_sync_inst.w_en_r, fifo_sync_inst.w_ptr_r, data_in_r, fifo_sync_inst.r_en_r, fifo_sync_inst.r_ptr_r, data_out_w);        
        $fwrite(fp, "%1b,%02d,%02d,%1b,%02d,%02d\n", fifo_sync_inst.w_en_r, fifo_sync_inst.w_ptr_r, data_in_r, fifo_sync_inst.r_en_r, fifo_sync_inst.r_ptr_r, data_out_w);        
    end

endmodule

vivado/fifo_sync_tb.vcd
$date
   Thu Sep 15 16:10:38 2022
$end
$version
  2019.2
$end
$timescale
  1ps
$end
$scope module fifo_sync_tb $end
$var integer 32 ! test_type $end
$var reg 1 " reset_r $end
$var reg 1 # clk_r $end
$var reg 1 $ w_en_r $end
$var reg 1 % r_en_r $end
$var wire 1 & fifo_full_w $end
$var wire 1 ' fifo_empty_w $end
$var reg 8 ( data_in_r [7:0] $end
$var wire 8 ) data_out_w [7:0] $end
$var real 32 * r_delay $end
$var real 32 + w_delay $end
$var integer 32 , i $end
$var integer 32 - fp $end
$var parameter 32 . DATA_WIDTH [31:0] $end
$var parameter 32 / ADDR_BITS [31:0] $end
$var parameter 32 0 N_REGS [31:0] $end
$var parameter 32 1 RW_ALWAYS [31:0] $end
$var parameter 32 2 W_ALWAYS_R_DELAYED [31:0] $end
$var parameter 32 3 W_NONE_R_ALWAYS [31:0] $end
$var parameter 32 4 WR_NOT_ALIGNED [31:0] $end
$scope module fifo_sync_inst $end
$var wire 1 5 resetn_i $end
$var wire 1 6 clk_i $end
$var wire 8 7 data_in [7:0] $end
$var wire 8 ) data_out [7:0] $end
$var wire 1 8 w_en $end
$var wire 1 9 r_en $end
$var wire 1 ' fifo_empty $end
$var wire 1 & fifo_full $end
$var reg 1 : w_en_r $end
$var reg 1 ; r_en_r $end
$var reg 4 < w_ptr_r [3:0] $end
$var reg 4 = r_ptr_r [3:0] $end
$var wire 1 > w_ptr_overflow $end
$var integer 32 ? i $end
$var parameter 32 @ DATA_WIDTH [31:0] $end
$var parameter 32 A ADDR_BITS [31:0] $end
$var parameter 32 B N_REGS [31:0] $end
$upscope $end
$upscope $end
$enddefinitions $end
#0
$dumpvars
b0 !
0"
0#
0$
0%
x&
x'
b0 (
bx )
r2 *
r6 +
b10000 ,
bx -
b1000 .
b100 /
b10000 0
b0 1
b1 2
b10 3
b11 4
05
06
b0 7
08
09
x:
x;
bx <
bx =
x>
bx ?
b1000 @
b100 A
b10000 B
$end
#500
1#
0&
1'
b10101 (
b0 )
16
b10101 7
0:
0;
b0 <
b0 =
0>
b10000 ?
#1000
0#
06
#1500
1#
b10111001 (
16
b10111001 7
b10000 ?
#2000
0#
06
#2500
1#
b11110011 (
16
b11110011 7
b10000 ?
#3000
0#
06
#3500
1#
b101001 (
16
b101001 7
b10000 ?
#4000
0#
06
#4500
1#
b1100100 (
16
b1100100 7
b10000 ?
#5000
1"
0#
15
06
#5500
1#
b10011011 (
16
b10011011 7
#6000
0#
1$
06
18
#6500
1#
b11000101 (
16
b11000101 7
1:
#7000
0#
06
#7500
1#
0'
b1111000 (
16
b1111000 7
b1 <
#8000
0#
1%
06
19
#8500
1#
b1010110 (
b11000101 )
16
b1010110 7
1;
b10 <
#9000
0#
06
#9500
1#
b10111010 (
b1111000 )
16
b10111010 7
b11 <
b1 =
#10000
0#
06
#10500
1#
b10100010 (
b1010110 )
16
b10100010 7
b100 <
b10 =
#11000
0#
06
#11500
1#
b10111001 (
b10111010 )
16
b10111001 7
b101 <
b11 =
#12000
0#
06
#12500
1#
b11010101 (
b10100010 )
16
b11010101 7
b110 <
b100 =
#13000
0#
06
#13500
1#
b11100111 (
b10111001 )
16
b11100111 7
b111 <
b101 =
#14000
0#
06
#14500
1#
b10110011 (
b11010101 )
16
b10110011 7
b1000 <
b110 =
#15000
0#
06
#15500
1#
b10101011 (
b11100111 )
16
b10101011 7
b1001 <
b111 =
#16000
0#
06
#16500
1#
b100010 (
b10110011 )
16
b100010 7
b1010 <
b1000 =
#17000
0#
06
#17500
1#
b11010101 (
b10101011 )
16
b11010101 7
b1011 <
b1001 =
#18000
0#
06
#18500
1#
b1100110 (
b100010 )
16
b1100110 7
b1100 <
b1010 =
#19000
0#
06
#19500
1#
b11111000 (
b11010101 )
16
b11111000 7
b1101 <
b1011 =
#20000
0#
06
#20500
1#
b111101 (
b1100110 )
16
b111101 7
b1110 <
b1100 =
#21000
0#
06
#21500
1#
b10011001 (
b11111000 )
16
b10011001 7
b1111 <
b1101 =
#22000
0#
06
#22500
1#
b100100 (
b111101 )
16
b100100 7
b0 <
b1110 =
1>
#23000
0#
06
#23500
1#
b1100000 (
b10011001 )
16
b1100000 7
b1 <
b1111 =
#24000
0#
06
#24500
1#
b11101110 (
b100100 )
16
b11101110 7
b10 <
b0 =
0>
#25000
0#
06
#25500
1#
b1010 (
b1100000 )
16
b1010 7
b11 <
b1 =
#26000
0#
06
#26500
1#
b11011000 (
b11101110 )
16
b11011000 7
b100 <
b10 =
#27000
0#
06
#27500
1#
b10101011 (
b1010 )
16
b10101011 7
b101 <
b11 =
#28000
0#
06
#28500
1#
b100011 (
b11011000 )
16
b100011 7
b110 <
b100 =
#29000
0#
06
#29500
1#
b11111100 (
b10101011 )
16
b11111100 7
b111 <
b101 =
#30000
0#
06
#30500
1#
b10001011 (
b100011 )
16
b10001011 7
b1000 <
b110 =
#31000
0#
06
#31500
1#
b10010001 (
b11111100 )
16
b10010001 7
b1001 <
b111 =
#32000
0#
06
#32500
1#
b1000 (
b10001011 )
16
b1000 7
b1010 <
b1000 =
#33000
0#
06
#33500
1#
b1100100 (
b10010001 )
16
b1100100 7
b1011 <
b1001 =
#34000
0#
06
#34500
1#
b111110 (
b1000 )
16
b111110 7
b1100 <
b1010 =
#35000
0#
06
#35500
1#
b101011 (
b1100100 )
16
b101011 7
b1101 <
b1011 =
#36000
0#
06
#36500
1#
b11100001 (
b111110 )
16
b11100001 7
b1110 <
b1100 =
#37000
0#
06
#37500
1#
b1001001 (
b101011 )
16
b1001001 7
b1111 <
b1101 =
#38000
0#
06
#38500
1#
b10111101 (
b11100001 )
16
b10111101 7
b0 <
b1110 =
1>
#39000
0#
06
#39500
1#
b1101001 (
b1001001 )
16
b1101001 7
b1 <
b1111 =
#40000
0#
06
#40500
1#
b10101110 (
b10111101 )
16
b10101110 7
b10 <
b0 =
0>
#41000
0#
06
#41500
1#
b1111011 (
b1101001 )
16
b1111011 7
b11 <
b1 =
#42000
0#
06
#42500
1#
b10100 (
b10101110 )
16
b10100 7
b100 <
b10 =
#43000
0#
06
#43500
1#
b10000 (
b1111011 )
16
b10000 7
b101 <
b11 =
#44000
0#
06
#44500
1#
b11000100 (
b10100 )
16
b11000100 7
b110 <
b100 =
#45000
0#
06
#45500
1#
b1010001 (
b10000 )
16
b1010001 7
b111 <
b101 =
#46000
0#
06
#46500
1#
b1111001 (
b11000100 )
16
b1111001 7
b1000 <
b110 =
#47000
0#
06
#47500
1#
b11110010 (
b1010001 )
16
b11110010 7
b1001 <
b111 =
#48000
0#
06
#48500
1#
b1001100 (
b1111001 )
16
b1001100 7
b1010 <
b1000 =
#49000
0#
06
#49500
1#
b10001100 (
b11110010 )
16
b10001100 7
b1011 <
b1001 =
#50000
0#
06
#50500
1#
b10000010 (
b1001100 )
16
b10000010 7
b1100 <
b1010 =
#51000
0#
06
#51500
1#
b10010001 (
b10001100 )
16
b10010001 7
b1101 <
b1011 =
#52000
0#
06
#52500
1#
b11011110 (
b10000010 )
16
b11011110 7
b1110 <
b1100 =
#53000
0#
06
#53500
1#
b11111010 (
b10010001 )
16
b11111010 7
b1111 <
b1101 =
#54000
0#
06
#54500
1#
b100 (
b11011110 )
16
b100 7
b0 <
b1110 =
1>
#55000
0#
06
#55500
1#
b10101010 (
b11111010 )
16
b10101010 7
b1 <
b1111 =
#56000
0#
06
#56500
1#
b1001 (
b100 )
16
b1001 7
b10 <
b0 =
0>
#57000
0#
06
#57500
1#
b10000111 (
b10101010 )
16
b10000111 7
b11 <
b1 =
#58000
0#
06
#58500
1#
b10111011 (
b1001 )
16
b10111011 7
b100 <
b10 =
#59000
0#
06
#59500
1#
b1100111 (
b10000111 )
16
b1100111 7
b101 <
b11 =
#60000
0#
06
#60500
1#
b10 (
b10111011 )
16
b10 7
b110 <
b100 =
#61000
0#
06
#61500
1#
b11000000 (
b1100111 )
16
b11000000 7
b111 <
b101 =
#62000
0#
06
#62500
1#
b10001 (
b10 )
16
b10001 7
b1000 <
b110 =
#63000
0#
06
#63500
1#
b1010 (
b11000000 )
16
b1010 7
b1001 <
b111 =
#64000
0#
06
#64500
1#
b1000111 (
b10001 )
16
b1000111 7
b1010 <
b1000 =
#65000
0#
06
#65500
1#
b11001101 (
b1010 )
16
b11001101 7
b1011 <
b1001 =
#66000
0#
06
#66500
1#
b11110000 (
b1000111 )
16
b11110000 7
b1100 <
b1010 =
#67000
0#
06
#67500
1#
b11001000 (
b11001101 )
16
b11001000 7
b1101 <
b1011 =
#68000
0#
06
#68500
1#
b1110 (
b11110000 )
16
b1110 7
b1110 <
b1100 =
#69000
0#
06
#69500
1#
b11 (
b11001000 )
16
b11 7
b1111 <
b1101 =
#70000
0#
06
#70500
1#
b11010011 (
b1110 )
16
b11010011 7
b0 <
b1110 =
1>
#71000
0#
06
#71500
1#
b11010100 (
b11 )
16
b11010100 7
b1 <
b1111 =
#72000
0#
06
#72500
1#
b1010000 (
b11010011 )
16
b1010000 7
b10 <
b0 =
0>
#73000
0#
06
#73500
1#
b1000100 (
b11010100 )
16
b1000100 7
b11 <
b1 =
#74000
0#
06
#74500
1#
b11101 (
b1010000 )
16
b11101 7
b100 <
b10 =
#75000
0#
06
#75500
1#
b11011101 (
b1000100 )
16
b11011101 7
b101 <
b11 =
#76000
0#
06
#76500
1#
b1000111 (
b11101 )
16
b1000111 7
b110 <
b100 =
#77000
0#
06
#77500
1#
b1110000 (
b11011101 )
16
b1110000 7
b111 <
b101 =
#78000
0#
06
#78500
1#
b110010 (
b1000111 )
16
b110010 7
b1000 <
b110 =
#79000
0#
06
#79500
1#
b10111 (
b1110000 )
16
b10111 7
b1001 <
b111 =
#80000
0#
06
#80500
1#
b110110 (
b110010 )
16
b110110 7
b1010 <
b1000 =
#81000
0#
06
#81500
1#
b11001110 (
b10111 )
16
b11001110 7
b1011 <
b1001 =
#82000
0#
06
#82500
1#
b1110100 (
b110110 )
16
b1110100 7
b1100 <
b1010 =
#83000
0#
06
#83500
1#
b1111100 (
b11001110 )
16
b1111100 7
b1101 <
b1011 =
#84000
0#
06
#84500
1#
b11000000 (
b1110100 )
16
b11000000 7
b1110 <
b1100 =
#85000
0#
06
#85500
1#
b100110 (
b1111100 )
16
b100110 7
b1111 <
b1101 =
#86000
0#
06
#86500
1#
b10010100 (
b11000000 )
16
b10010100 7
b0 <
b1110 =
1>
#87000
0#
06
#87500
1#
b1110110 (
b100110 )
16
b1110110 7
b1 <
b1111 =
#88000
0#
06
#88500
1#
b10010100 )
16
b10 <
b0 =
0>
#89000
0#
06
#89500
1#
b10001000 (
b1110110 )
16
b10001000 7
b11 <
b1 =
#90000
0#
06
#90500
1#
b1110010 (
16
b1110010 7
b100 <
b10 =
#91000
0#
06
#91500
1#
b10110110 (
b10001000 )
16
b10110110 7
b101 <
b11 =
#92000
0#
06
#92500
1#
b110000 (
b1110010 )
16
b110000 7
b110 <
b100 =
#93000
0#
06
#93500
1#
b10000110 (
b10110110 )
16
b10000110 7
b111 <
b101 =
#94000
0#
06
#94500
1#
b101100 (
b110000 )
16
b101100 7
b1000 <
b110 =
#95000
0#
06
#95500
1#
b10100101 (
b10000110 )
16
b10100101 7
b1001 <
b111 =
#96000
0#
06
#96500
1#
b10000 (
b101100 )
16
b10000 7
b1010 <
b1000 =
#97000
0#
06
#97500
1#
b11110 (
b10100101 )
16
b11110 7
b1011 <
b1001 =
#98000
0#
06
#98500
1#
b11011011 (
b10000 )
16
b11011011 7
b1100 <
b1010 =
#99000
0#
06
#99500
1#
b10111111 (
b11110 )
16
b10111111 7
b1101 <
b1011 =
#100000
0#
06
#100500
1#
b10100101 (
b11011011 )
16
b10100101 7
b1110 <
b1100 =
#101000
0#
06
#101500
1#
b10000111 (
b10111111 )
16
b10000111 7
b1111 <
b1101 =
#102000
0#
06
#102500
1#
b11100100 (
b10100101 )
16
b11100100 7
b0 <
b1110 =
1>
#103000
0#
06
#103500
1#
b10110101 (
b10000111 )
16
b10110101 7
b1 <
b1111 =
#104000
0#
06
#104500
1#
b100101 (
b11100100 )
16
b100101 7
b10 <
b0 =
0>
#105000
0#
06
#105500
1#
b1000000 (
b10110101 )
16
b1000000 7
b11 <
b1 =
#106000
0#
06
#106500
1#
b11110100 (
b100101 )
16
b11110100 7
b100 <
b10 =
#107000
0#
06
#107500
1#
b11001010 (
b1000000 )
16
b11001010 7
b101 <
b11 =
#108000
0#
06
#108500
1#
b1000111 (
b11110100 )
16
b1000111 7
b110 <
b100 =
#109000
0#
0$
0%
06
08
09
#109500
1#
b1011001 (
b0 )
16
b1011001 7
0:
0;
b111 <
b101 =
#110000
0#
06
#110500
1#
b0 (
16
b0 7
#111000
0#
06
#111500
1#
b11101011 (
16
b11101011 7
#112000
0#
06
#112500
1#
b11001 (
16
b11001 7
#113000
0#
06
#113500
1#
b1110100 (
16
b1110100 7
#114000
0#
06
#114500
1#
b10110111 (
16
b10110111 7
#115000
0#
06
#115500
1#
b11011111 (
16
b11011111 7
#116000
0#
06
#116500
1#
b1001101 (
16
b1001101 7
#117000
0#
06
#117500
1#
b110111 (
16
b110111 7
#118000
0#
06
#118500
1#
b11001011 (
16
b11001011 7
#119000
0#
06
#119500
1#
b11100101 (
16
b11100101 7
#120000
0#
06
#120500
1#
b101100 (
16
b101100 7
#121000
0#
06
#121500
1#
b11 (
16
b11 7
#122000
0#
06
#122500
1#
b11000101 (
16
b11000101 7
#123000
0#
06
#123500
1#
b11111000 (
16
b11111000 7
#124000
0#
06
#124500
1#
b10111010 (
16
b10111010 7
#125000
0#
06
#125500
1#
b10010 (
16
b10010 7
#126000
0#
06
#126500
1#
b11011111 (
16
b11011111 7
#127000
0#
06
#127500
1#
b1100110 (
16
b1100110 7
#128000
0#
06
#128500
1#
b10010100 (
16
b10010100 7
#129000
0#
06
#129500
1#
b100101 (
16
b100101 7
#130000
0#
06
#130500
1#
b11011110 (
16
b11011110 7
#131000
0#
06
#131500
1#
b11001110 (
16
b11001110 7
#132000
0#
06
#132500
1#
b10110110 (
16
b10110110 7
#133000
0#
06
#133500
1#
b10111110 (
16
b10111110 7
#134000
0#
06
#134500
1#
b10110100 (
16
b10110100 7
#135000
0#
06
#135500
1#
b1001100 (
16
b1001100 7
#136000
0#
06
#136500
1#
b11100100 (
16
b11100100 7
#137000
0#
06
#137500
1#
b10101 (
16
b10101 7
#138000
0#
06
#138500
1#
b10011010 (
16
b10011010 7
#139000
0#
06
#139500
1#
b11011 (
16
b11011 7
#140000
0#
06
#140500
1#
b1010011 (
16
b1010011 7
#141000
0#
06
#141500
1#
b11010000 (
16
b11010000 7
#142000
0#
06
#142500
1#
b1100111 (
16
b1100111 7
#143000
0#
06
#143500
1#
b10110111 (
16
b10110111 7
#144000
0#
06
#144500
1#
b1100101 (
16
b1100101 7
#145000
0#
06
#145500
1#
b11 (
16
b11 7
#146000
0#
06
#146500
1#
b11010011 (
16
b11010011 7
#147000
0#
06
#147500
1#
b111000 (
16
b111000 7
#148000
0#
06
#148500
1#
b1010011 (
16
b1010011 7
#149000
0#
06
#149500
1#
b10111010 (
16
b10111010 7
#150000
0#
06
#150500
1#
b11110000 (
16
b11110000 7
#151000
0#
06
#151500
1#
b111000 (
16
b111000 7
#152000
0#
06
#152500
1#
b111101 (
16
b111101 7
#153000
0#
06
#153500
1#
b1000100 (
16
b1000100 7
#154000
0#
06
#154500
1#
b11101111 (
16
b11101111 7
#155000
0#
06
#155500
1#
b10000 (
16
b10000 7
#156000
0#
06
#156500
1#
b1111110 (
16
b1111110 7
#157000
0#
06
#157500
1#
b1100000 (
16
b1100000 7
#158000
0#
06
#158500
1#
b11000111 (
16
b11000111 7
